robosandbox/__init__.py
robosandbox/geometry/__init__.py
robosandbox/geometry/mesh_utilities.py
robosandbox/geometry/Link/CylinderLink.py
robosandbox/geometry/Link/__init__.py
robosandbox/models/__init__.py
robosandbox/models/DH/Panda.py
robosandbox/models/DH/Puma560.py
robosandbox/models/DH/Stanford.py
robosandbox/models/DH/UR5.py
robosandbox/models/DH/__init__.py
robosandbox/models/DH/Generic/Generic.py
robosandbox/models/DH/Generic/GenericFive.py
robosandbox/models/DH/Generic/GenericFour.py
robosandbox/models/DH/Generic/GenericSeven.py
robosandbox/models/DH/Generic/GenericSix.py
robosandbox/models/DH/Generic/GenericThree.py
robosandbox/models/DH/Generic/GenericTwo.py
robosandbox/models/DH/Generic/__init__.py
robosandbox/models/DHRoboLink/__init__.py
robosandbox/models/DHRoboLink/Generic/GenericFour.py
robosandbox/models/DHRoboLink/Generic/__init__.py
robosandbox/models/MR/ModernRobotics.py
robosandbox/models/MR/__init__.py
robosandbox/models/MR/utils.py
robosandbox/models/MR/Generic/GenericFour.py
robosandbox/models/MR/Generic/GenericThree.py
robosandbox/models/MR/Generic/__init__.py
robosandbox/models/URDF/Generic.py
robosandbox/models/URDF/GenericFive.py
robosandbox/models/URDF/GenericFour.py
robosandbox/models/URDF/GenericSeven.py
robosandbox/models/URDF/GenericSix.py
robosandbox/models/URDF/GenericThree.py
robosandbox/models/URDF/GenericTwo.py
robosandbox/models/URDF/Model.py
robosandbox/models/URDF/Panda.py
robosandbox/models/URDF/Puma560.py
robosandbox/models/URDF/UR5.py
robosandbox/models/URDF/__init__.py
robosandbox/models/URDF/dh_to_urdf.py
robosandbox/models/URDF/generic_dh_robot.py
robosandbox/models/URDF/teach_G4.py
robosandbox/optimization/__init__.py
robosandbox/optimization/problem.py
robosandbox/optimization/sweeper.py
robosandbox/performance/__init__.py
robosandbox/performance/workspace/WorkSpace.py
robosandbox/performance/workspace/__init__.py
robosandbox/performance/workspace/base_workspace.py
robosandbox-0.0.1.dist-info/METADATA
robosandbox-0.0.1.dist-info/WHEEL
robosandbox-0.0.1.dist-info/entry_points.txt
robosandbox-0.0.1.dist-info/top_level.txt
robosandbox-0.0.1.dist-info/RECORD
