Metadata-Version: 2.4
Name: robosandbox
Version: 0.0.1
Summary: An Open-Source Python Framework for Manipulator Design and Analysis
Author-email: Chaoyue Fei <chaoyue.fei@vub.be>
Maintainer-email: Chaoyue Fei <chaoyue.fei@vub.be>
Keywords: robotics,manipulator,design,analysis,simulation
Requires-Python: >=3.8
Requires-Dist: numpy<2
Requires-Dist: websockets<=12.0
Requires-Dist: roboticstoolbox_python>=1.1.1
Requires-Dist: plotly
Requires-Dist: pytest
Requires-Dist: pandas
Requires-Dist: tqdm
Requires-Dist: ipykernel
Requires-Dist: kaleido
Requires-Dist: nbformat>=4.2.0
Requires-Dist: numpy-stl
Requires-Dist: dash
Requires-Dist: dash-bootstrap-components
Requires-Dist: pywebview
Requires-Dist: pymoo
Provides-Extra: dev
Requires-Dist: check-manifest; extra == "dev"
Provides-Extra: collision
Requires-Dist: pybullet<=2.0.0; extra == "collision"
Provides-Extra: test
Requires-Dist: pytest>=7.0.0; extra == "test"
Requires-Dist: pytest-cov>=4.0.0; extra == "test"
